{"bg":{"x":0,"y":0,"width":2938,"height":1660},
"-3-3":{"x":964,"y":924,"width":1260,"height":736},
"-3-2":{"x":1341,"y":0,"width":1597,"height":1574},
"-3-1":{"x":0,"y":232,"width":1337,"height":1428},
"-2-4":{"x":766,"y":558,"width":1097,"height":1102},
"-2-3":{"x":0,"y":172,"width":1015,"height":1482},
"-2-2":{"x":1303,"y":378,"width":1575,"height":1036},
"-2-1":{"x":1953,"y":0,"width":985,"height":1374},
"-1-9":{"x":1033,"y":539,"width":1637,"height":1121},
"-1-8":{"x":2765,"y":0,"width":173,"height":394},
"-1-7":{"x":1534,"y":978,"width":651,"height":429},
"-1-6":{"x":696,"y":542,"width":326,"height":388},
"-1-5":{"x":80,"y":354,"width":320,"height":325},
"-1-4":{"x":1438,"y":867,"width":320,"height":325},
"-1-3":{"x":563,"y":75,"width":230,"height":216},
"-1-2":{"x":200,"y":454,"width":230,"height":216},
"-1-1":{"x":1469,"y":870,"width":230,"height":216},
"0":{"x":0,"y":0,"width":2938,"height":1660},
"1-11":{"x":2536,"y":1522,"width":308,"height":80},
"1-10":{"x":837,"y":545,"width":236,"height":218},
"1-9":{"x":1248,"y":872,"width":236,"height":104},
"1-8":{"x":837,"y":659,"width":236,"height":104},
"1-7":{"x":1880,"y":1193,"width":236,"height":104},
"1-6":{"x":2308,"y":1397,"width":236,"height":104},
"1-5":{"x":1247,"y":594,"width":236,"height":102},
"1-4":{"x":1673,"y":816,"width":236,"height":102},
"1-3":{"x":2093,"y":1021,"width":236,"height":102},
"1-2":{"x":2523,"y":1233,"width":236,"height":102},
"1-1":{"x":27,"y":528,"width":1039,"height":161},
"2-1":{"x":942,"y":200,"width":1996,"height":1117},
}